README.rst
setup.py
mock_import/__init__.py
mock_import.egg-info/PKG-INFO
mock_import.egg-info/SOURCES.txt
mock_import.egg-info/dependency_links.txt
mock_import.egg-info/requires.txt
mock_import.egg-info/top_level.txt