Metadata-Version: 1.0
Name: mock-import
Version: 0.0.2
Summary: A mocking functions for imports
Home-page: http://github.com/posener/mock-import.git
Author: Eyal Posener
Author-email: posener@gmail.com
License: UNKNOWN
Keywords: mock import
Platform: UNKNOWN
